PCSS/__init__.py
PCSS/hash.py
PCSS/util.py
projxon_cyber_security_system-0.3.4.dist-info/LICENSE.txt
projxon_cyber_security_system-0.3.4.dist-info/METADATA
projxon_cyber_security_system-0.3.4.dist-info/WHEEL
projxon_cyber_security_system-0.3.4.dist-info/top_level.txt
projxon_cyber_security_system-0.3.4.dist-info/RECORD
