Metadata-Version: 2.1
Name: projxon-cyber-security-system
Version: 0.3.4
Summary: A fast and unbreakable encrytion system.
Download-URL: https://github.com/hg0428/Projxon-Cyber-Security-System/archive/refs/tags/stable-0.3.4.tar.gz
Author: Hudson Gouge
Classifier: Intended Audience :: Developers
Classifier: Topic :: Software Development :: Build Tools
Classifier: Programming Language :: Python :: 3
Classifier: License :: OSI Approved :: MIT License
Classifier: Operating System :: OS Independent
Requires-Python: >=3.7
License-File: LICENSE.txt
Requires-Dist: bitarray
Requires-Dist: passlib
Requires-Dist: uuid
